dbbridge/__init__.py
dbbridge/aws_db.py
dbbridge/azure_db.py
dbbridge/db_connection.py
dbbridge/db_manager.py
dbbridge/local_db.py
dbbridge/rds_execute.py
dbbridge-0.0.29.dist-info/LICENSE
dbbridge-0.0.29.dist-info/METADATA
dbbridge-0.0.29.dist-info/WHEEL
dbbridge-0.0.29.dist-info/top_level.txt
dbbridge-0.0.29.dist-info/RECORD
