Metadata-Version: 2.1
Name: dbbridge
Version: 0.0.29
Summary: A unified cloud db package for AWS, Azure, and GCP
Author: Aaditya Muleva
Author-email: aaditya.muleva@trovehealth.io
License: MIT
Classifier: Programming Language :: Python :: 3
Classifier: License :: OSI Approved :: MIT License
Classifier: Operating System :: OS Independent
Classifier: Development Status :: 5 - Production/Stable
Classifier: Intended Audience :: Developers
Classifier: Topic :: Software Development :: Libraries :: Python Modules
Requires-Python: >=3.6
License-File: LICENSE
Requires-Dist: boto3>=1.20.0
Requires-Dist: pymysql>=1.0.2
Requires-Dist: pyodbc>=4.0.32
Requires-Dist: google-auth>=2.0.0
Requires-Dist: google-auth-oauthlib>=0.4.0
Requires-Dist: cryptography>=3.3.2
Requires-Dist: pyopenssl>=20.0.1
